PyEnviron/PyEnviron.py
PyEnviron/__init__.py
PyEnviron-0.0.4.dist-info/METADATA
PyEnviron-0.0.4.dist-info/RECORD
PyEnviron-0.0.4.dist-info/WHEEL
PyEnviron-0.0.4.dist-info/top_level.txt
