Metadata-Version: 2.1
Name: PyEnviron
Version: 0.0.4
Summary: PyEnvirons is a higher level API of pygame to easily design, devolop and debug environments for your unsupervised AI agent. It is under rapid development and features will be added almost every single day.
Home-page: https://github.com/TheG3ntleman/PyEnvirons
Author: TheG3ntleman
Author-email: sriabhirath12@gmail.com
License: UNKNOWN
Platform: UNKNOWN
